ChemMap/__init__.py
ChemMap/chem_map.py
ChemMap/chem_requester.py
ChemMap/enums.py
ChemMap/utils.py
chem_map-0.0.1.dist-info/LICENSE
chem_map-0.0.1.dist-info/METADATA
chem_map-0.0.1.dist-info/WHEEL
chem_map-0.0.1.dist-info/RECORD
