Metadata-Version: 2.3
Name: chem-map
Version: 0.0.1
Summary: a Python library that automatically annotates metabolomics data with proteomics/metagenomics metadata using existing databases.
Author: Albert Anguera Sempere
Author-email: albert.anguera.sempere@gmail.com
Requires-Python: >=3.10
Classifier: Programming Language :: Python :: 3
Classifier: License :: OSI Approved :: MIT License
Requires-Dist: libchebipy (>=1.0.10,<2.0.0)
Requires-Dist: numpy (>=2.2.3,<3.0.0)
Requires-Dist: pandas (>=2.2.3,<3.0.0)
Requires-Dist: rdkit (>=2024.9.5,<2025.0.0)
Requires-Dist: requests (>=2.32.3,<3.0.0)
Requires-Dist: tqdm (>=4.67.1,<5.0.0)
Project-URL: Homepage, https://github.com/anguera5/ChemMap
